linkedin_api/__init__.py
linkedin_api/clients/__init__.py
linkedin_api/clients/auth/__init__.py
linkedin_api/clients/auth/client.py
linkedin_api/clients/auth/response.py
linkedin_api/clients/auth/response_formatter.py
linkedin_api/clients/auth/utils/__init__.py
linkedin_api/clients/auth/utils/oauth.py
linkedin_api/clients/common/__init__.py
linkedin_api/clients/common/response.py
linkedin_api/clients/common/response_formatter.py
linkedin_api/clients/restli/__init__.py
linkedin_api/clients/restli/client.py
linkedin_api/clients/restli/response.py
linkedin_api/clients/restli/response_formatter.py
linkedin_api/clients/restli/types.py
linkedin_api/clients/restli/utils/__init__.py
linkedin_api/clients/restli/utils/api.py
linkedin_api/clients/restli/utils/decoder.py
linkedin_api/clients/restli/utils/encoder.py
linkedin_api/clients/restli/utils/query_tunneling.py
linkedin_api/clients/restli/utils/restli.py
linkedin_api/common/__init__.py
linkedin_api/common/constants.py
linkedin_api/common/errors.py
linkedin_api_client-0.2.0.dist-info/LICENSE.md
linkedin_api_client-0.2.0.dist-info/WHEEL
linkedin_api_client-0.2.0.dist-info/METADATA
linkedin_api_client-0.2.0.dist-info/RECORD
