Metadata-Version: 2.1
Name: linkedin-api-client
Version: 0.2.0
Summary: Official Python client library for LinkedIn APIs
Home-page: https://github.com/linkedin-developers/linkedin-api-python-client
License: Proprietary
Keywords: linkedin,api,rest.li
Author: Steven Shimizu
Author-email: sshimizu@linkedin.com
Requires-Python: >=3.7,<4.0
Classifier: Development Status :: 4 - Beta
Classifier: License :: Other/Proprietary License
Classifier: Programming Language :: Python
Classifier: Programming Language :: Python :: 3
Classifier: Programming Language :: Python :: 3.7
Classifier: Programming Language :: Python :: 3.8
Classifier: Programming Language :: Python :: 3.9
Classifier: Programming Language :: Python :: 3.10
Classifier: Programming Language :: Python :: 3.11
Classifier: Programming Language :: Python :: 3
Requires-Dist: requests
Project-URL: Documentation, https://github.com/linkedin-developers/linkedin-api-python-client
Project-URL: Repository, https://github.com/linkedin-developers/linkedin-api-python-client
